LICENCE
fgen/__init__.py
fgen/cmake_help.py
fgen/commands/__init__.py
fgen/commands/base.py
fgen/commands/generate.py
fgen/data_models/__init__.py
fgen/data_models/fortran_derived_type.py
fgen/data_models/method.py
fgen/data_models/module.py
fgen/data_models/module_enum_defining.py
fgen/data_models/module_requirement.py
fgen/data_models/multi_return.py
fgen/data_models/package.py
fgen/data_models/package_shared_elements.py
fgen/data_models/serialisation.py
fgen/data_models/unitless_value.py
fgen/data_models/value.py
fgen/f2py.py
fgen/fortran_parsing.py
fgen/jinja_environment.py
fgen/main.py
fgen/py.typed
fgen/wrapper_building/__init__.py
fgen/wrapper_building/formatting.py
fgen/wrapper_building/fortran_manager_module/__init__.py
fgen/wrapper_building/fortran_manager_module/fortran-manager-module.f90.jinja
fgen/wrapper_building/fortran_wrapper_module/__init__.py
fgen/wrapper_building/fortran_wrapper_module/fortran-wrapper-module.f90.jinja
fgen/wrapper_building/fortran_wrapper_module/module-level-docstring.f90.jinja
fgen/wrapper_building/fortran_wrapper_module/module-use-requirements.f90.jinja
fgen/wrapper_building/fortran_wrapper_module/module-use-statements.f90.jinja
fgen/wrapper_building/fortran_wrapper_module/provided-type-method-no-return.f90.jinja
fgen/wrapper_building/fortran_wrapper_module/provided-type-setter.f90.jinja
fgen/wrapper_building/python_enums_module/__init__.py
fgen/wrapper_building/python_enums_module/python-enum-definition.py.jinja
fgen/wrapper_building/python_enums_module/python-enums-module.py.jinja
fgen/wrapper_building/python_init_module/__init__.py
fgen/wrapper_building/python_init_module/python-init-module.py.jinja
fgen/wrapper_building/python_wrapper_module/__init__.py
fgen/wrapper_building/python_wrapper_module/getters-and-setters.py.jinja
fgen/wrapper_building/python_wrapper_module/methods.py.jinja
fgen/wrapper_building/python_wrapper_module/module-imports-requirements.py.jinja
fgen-0.6.1.dist-info/LICENCE
fgen-0.6.1.dist-info/METADATA
fgen-0.6.1.dist-info/WHEEL
fgen-0.6.1.dist-info/entry_points.txt
fgen-0.6.1.dist-info/RECORD
