Metadata-Version: 2.1
Name: fgen
Version: 0.6.1
Summary: Automatically generate wrapper to integrate Fortran and Python
Home-page: https://gitlab.com/magicc/fgen
License: BSD-3-Clause
Keywords: fortran
Author: Zebedee Nicholls
Author-email: zebedee.nicholls@climate-energy-college.org
Requires-Python: >=3.9,<4.0
Classifier: Development Status :: 4 - Beta
Classifier: Intended Audience :: Developers
Classifier: Intended Audience :: Science/Research
Classifier: License :: OSI Approved :: BSD License
Classifier: Operating System :: OS Independent
Classifier: Programming Language :: Python
Classifier: Programming Language :: Python :: 3
Classifier: Programming Language :: Python :: 3.9
Classifier: Programming Language :: Python :: 3.10
Classifier: Programming Language :: Python :: 3.11
Classifier: Programming Language :: Python :: 3.12
Classifier: Topic :: Scientific/Engineering
Provides-Extra: templates
Requires-Dist: attrs (>=23.0.0,<24.0.0)
Requires-Dist: black (>=23.3.0,<24.0.0) ; extra == "templates"
Requires-Dist: cattrs (>=23.0.0,<24.0.0)
Requires-Dist: click (>=8.0.0,<9.0.0)
Requires-Dist: jinja2 (>=3.1.2,<4.0.0) ; extra == "templates"
Requires-Dist: loguru (>=0.7.2,<0.8.0)
Requires-Dist: numpy (>1.23)
Requires-Dist: pint
Requires-Dist: pyyaml (>=6.0,<7.0)
Requires-Dist: typing-extensions (>=4.9.0,<5.0.0)
